{
    "list1": [
        {
            "press": "머니S",
            "logo_url": "https://mimgnews.pstatic.net/image/upload/office_logo/417/2017/12/27/logo_417_38_20171227165627.png",
            "date": "11:01 AM 2022/01/12",
            "title": "삼성전자, 시총 468조원 ‘부동의 1위’… 네이버 3위 등극",
            "section": "경제",
            "content": "삼성전자가 시가총액 1위를 수성했다. 사진 뉴시스 최근 1년 새 시가총액 시총 100대 기업의 순위가 크게 ",
            "url": "https://news.naver.com/main/read.naver?mode=LSD&mid=sec&sid1=101&oid=417&aid=0000774592",
            "name": "하이닉스",
            "types": "IDM",
            "like_cnt": 8,
            "recom_react_cnt": 13151,
            "com_cnt": 6,
            "summaries": "['삼성전자의 시총은 지난해 초 495조4919억원에서 올해 총 469조2249억원으로 줄었지만 여전히 압도적인 1위를 유지했다.', '메리츠금융지주는 작년 초 시총 순위 194위 1조2972억원 에서 올해 초 65위 6조975억원 로 128계단 점프했다.', '사진 뉴시스 최근 1년 새 시가총액 시총 100대 기업의 순위가 크게 뒤바뀐 가운데 삼성전자가 부동의 1위를 지킨 것으로 나타났다.']",
            "hashtag": [
                {
                    "hash1": "#올해"
                },
                {
                    "hash2": "#순위"
                },
                {
                    "hash3": "#계단"
                },
                {
                    "hash4": "#기업"
                }
            ]
        },
        {
            "press": "전자신문",
            "logo_url": "https://mimgnews.pstatic.net/image/upload/office_logo/030/2017/12/27/logo_030_38_20171227162327.png",
            "date": "10:23 AM 2022/01/12",
            "title": "델 테크놀로지스, 친환경 소재 접목 고성능 노트북·모니터 출시",
            "section": "IT",
            "content": "델 테크놀로지스는 인텔 12세대 코어 프로세서를 탑재한 고성능 프리미엄 노트북 XPS 13 플러스 와 화상 ",
            "url": "https://news.naver.com/main/read.naver?mode=LSD&mid=sec&sid1=105&oid=030&aid=0002993219",
            "name": "인텔",
            "types": "IDM",
            "like_cnt": 0,
            "recom_react_cnt": 4874,
            "com_cnt": 0,
            "summaries": "['델 울트라샤프 32 4K 비디오 콘퍼런싱 모니터 U3223QZ 는 화상 회의에 최적화된 제품으로 웹캠과 IPS 블랙 패널 기술을 탑재한 31.5인치 4K 모니터이다.', '델 테크놀로지스는 인텔 12세대 코어 프로세서를 탑재한 고성능 프리미엄 노트북 XPS 13 플러스 와 화상 회의에 최적화된 델 울트라샤프 32 4K 비디오 콘퍼런싱 모니터 를 공개했다고 12일 밝혔다.', '특히 이 제품은 델의 친환경 정책에 따라 불필요한 제조공정을 과감히 생략하고 재활용 가능한 부품과 포장재를 도입했다.']",
            "hashtag": [
                {
                    "hash1": "#모니터"
                },
                {
                    "hash2": "#제품"
                },
                {
                    "hash3": "#울트라"
                },
                {
                    "hash4": "#플러스"
                }
            ]
        },
        {
            "press": "헤럴드경제",
            "logo_url": "https://mimgnews.pstatic.net/image/upload/office_logo/016/2017/12/27/logo_016_38_20171227161627.png",
            "date": "7:47 PM 2022/01/12",
            "title": "“이게 150만원 실화야?” 삼성 야심작, 아이폰보다 비싸다?",
            "section": "IT",
            "content": "삼성 올 전략 스마트폰 갤럭시S22 렌더링 이미지 공개 임박 삼성 야심작 가격은 얼마 삼성전자의 올해 첫 전",
            "url": "https://news.naver.com/main/read.naver?mode=LSD&mid=sec&sid1=105&oid=016&aid=0001936810",
            "name": "삼성전자",
            "types": "IDM",
            "like_cnt": 86,
            "recom_react_cnt": 2215,
            "com_cnt": 136,
            "summaries": "['12일 IT팁스터 정보유출가 Chunvn888는 삼성전자의 전략 스마트폰 갤럭시S22의 기본 모델 가격이 전작인 갤럭시S21보다 12만원 100달러 더 비싼 107만원 899달러 에 달할 것으로 전망했다.', '아이폰14 프로 예상 이미지 갤럭시S22 시리즈의 가격 인상은 스마트폰 부품 공급난 때문으로 보인다.', '갤럭시S22 가격이 올해 출시될 애플의 신형 아이폰 아이폰14 시리즈와 비슷하거나 오히려 더 비쌀수도 있다.']",
            "hashtag": [
                {
                    "hash1": "#가격"
                },
                {
                    "hash2": "#아이"
                },
                {
                    "hash3": "#모델"
                },
                {
                    "hash4": "#스마트"
                }
            ]
        },
        {
            "press": "아시아경제",
            "logo_url": "https://mimgnews.pstatic.net/image/upload/office_logo/277/2017/12/27/logo_277_38_20171227165227.png",
            "date": "2:05 PM 2022/01/12",
            "title": "블룸버그 \"中, 韓 바짝 추격\"…기술패권 고삐 죄는 中",
            "section": "세계",
            "content": " 견제에도 화웨이 지난해 특허건수 5위로 뛰어올라 삼성은 2위 유지 중부 정보기술 IT 업체 화웨이가 지난해",
            "url": "https://news.naver.com/main/read.naver?mode=LSD&mid=sec&sid1=104&oid=277&aid=0005029524",
            "name": "삼성전자",
            "types": "IDM",
            "like_cnt": 2,
            "recom_react_cnt": 1935,
            "com_cnt": 1,
            "summaries": "['블룸버그통신은 화웨이가 9위에서 5위로 점프한 것은 다른 기업들의 특허 취득 건수가 7 감소한 것이 한 요인 이라고 분석했다.', '삼성전자가 글로벌 특허 보유 누적 건수 1위를 유지한 가운데 2 7위는 화웨이와 중국사회과학원을 포함한 중국 기업 기관이 휩쓸었다.', '10일 현지시간 블룸버그통신이 특허분석 플랫폼 IFI클레임스 보고서를 인용해 보도한 바에 따르면 화웨이는 지난해 미국에서 2770건의 특허를 취득한 것으로 나타났다.']",
            "hashtag": [
                {
                    "hash1": "#특허"
                },
                {
                    "hash2": "#건수"
                },
                {
                    "hash3": "#지난해"
                },
                {
                    "hash4": "#취득"
                }
            ]
        },
        {
            "press": "파이낸셜뉴스",
            "logo_url": "https://mimgnews.pstatic.net/image/upload/office_logo/014/2020/03/06/logo_014_38_20200306153406.png",
            "date": "6:25 PM 2022/01/12",
            "title": "[김경민의 적시타]LCD값 대폭락…국내기업 사실상 사업 철수",
            "section": "경제",
            "content": " 과 수년간 치킨게임 계속되며 패널가격 정점후 반년새 반토막 삼성 LGD 등 생산 줄이는 대신 프리미엄 시장",
            "url": "https://news.naver.com/main/read.naver?mode=LSD&mid=sec&sid1=101&oid=014&aid=0004771276",
            "name": "삼성전자",
            "types": "IDM",
            "like_cnt": 17,
            "recom_react_cnt": 1856,
            "com_cnt": 6,
            "summaries": "[' 과 수년간 치킨게임 계속되며 패널가격 정점후 반년새 반토막 삼성 LGD 등 생산 줄이는 대신 프리미엄 시장 OLED 선점나서 코로나19에 따른 펜트업 보복소비 수요가 끝나면서 액정표시장치 LCD 패널 가격이 반년 만에 반토막이 나자 국내 디스플레이 업체들의 철수 움직임이 본격화되고 있다.', '12일 시장조사업체 DSCC에 따르면 지난해 여름 급등한 LCD 패널 가격이 피크아웃 정점을 찍고 내려오는 현상 하면서 현재는 고점 대비 반값에도 미치지 못하는 것으로 나타났다.', '현재 OLED 세트를 만드는 업체 중 삼성전자와 중국의 TCL 2곳을 빼고 모든 업체들이 LG디스플레이의 패널을 공급받고 있다.']",
            "hashtag": [
                {
                    "hash1": "#디스플레이"
                },
                {
                    "hash2": "#패널"
                },
                {
                    "hash3": "#가격"
                },
                {
                    "hash4": "#달러"
                }
            ]
        },
        {
            "press": "TV조선",
            "logo_url": "https://mimgnews.pstatic.net/image/upload/office_logo/448/2018/08/30/logo_448_38_20180830113230.png",
            "date": "4:51 PM 2022/01/12",
            "title": "美 긴축 우려 완화에 코스피, 1.54% '반등'",
            "section": "경제",
            "content": "기관 10일만에 순매수 코스피가 외국인과 기관의 매수세에 힘입어 올 들어 가장 큰 상승률로 마감했다. 코스닥",
            "url": "https://news.naver.com/main/read.naver?mode=LSD&mid=sec&sid1=101&oid=448&aid=0000348802",
            "name": "삼성전자",
            "types": "IDM",
            "like_cnt": 0,
            "recom_react_cnt": 1582,
            "com_cnt": 0,
            "summaries": "['12일 한국거래소에 따르면 코스피는 전거래일 대비 45.10포인트 1.54 상승한 2972.48으로 장을 마쳤다.', '투자자별로 개인은 1640억원 순매도한 반면 외국인과 기관은 각각 358억원 1324억원 순매수했다.', '투자자별로 외국인과 기관이 각각 4553억원 6066억원 순매수한 반면 개인은 1조718억원 순매도했다.']",
            "hashtag": [
                {
                    "hash1": "#대비"
                },
                {
                    "hash2": "#상승"
                },
                {
                    "hash3": "#거래"
                },
                {
                    "hash4": "#기관"
                }
            ]
        },
        {
            "press": "한국경제",
            "logo_url": "https://mimgnews.pstatic.net/image/upload/office_logo/015/2017/12/27/logo_015_38_20171227161527.png",
            "date": "11:10 AM 2022/01/12",
            "title": "이재용도 찾아간 그곳…'60평 화재' 사고에 삼성 '초비상'",
            "section": "경제",
            "content": "EUV 노광장비 독점생산 기업 ASML서 화재 글로벌 반도체 기업들 화들짝 웨이퍼 클램프 생산 설비 화재 영",
            "url": "https://news.naver.com/main/read.naver?mode=LSD&mid=sec&sid1=101&oid=015&aid=0004651905",
            "name": "하이닉스",
            "types": "IDM",
            "like_cnt": 16,
            "recom_react_cnt": 1454,
            "com_cnt": 39,
            "summaries": "['EUV 노광장비 독점생산 기업 ASML서 화재 글로벌 반도체 기업들 화들짝 웨이퍼 클램프 생산 설비 화재 영향 받아 반도체 장비 수요공급 불균형 심화 가능성 이재용 삼성전자 부회장이 202년 10월 네덜란드 에인트호번에 위치한 ASML 본사를 찾아 김기남 전 삼성전자 DS부문장 부회장과 EUV 장비를 살펴보는 모습.', '업계에 따르면 올해 생산 예정인 ASML의 EUV 장비는 이미 100 예약 완료됐으며 삼성전자가 18대 SK하이닉스가 4대를 확보한 것으로 알려졌다.', '반도체 생산의 핵심인 극자외선 EUV 노광 장비 독점 생산 기업 ASML에서 화재가 발생했다.']",
            "hashtag": [
                {
                    "hash1": "#장비"
                },
                {
                    "hash2": "#생산"
                },
                {
                    "hash3": "#화재"
                },
                {
                    "hash4": "#반도체"
                }
            ]
        },
        {
            "press": "한국경제",
            "logo_url": "https://mimgnews.pstatic.net/image/upload/office_logo/015/2017/12/27/logo_015_38_20171227161527.png",
            "date": "9:02 PM 2022/01/12",
            "title": "삼성·하이닉스 '매출 신기록' 이유 있네…\"韓, 반도체장비 최대 투자국\"",
            "section": "경제",
            "content": "국제반도체장비재료협회 분석 올해 반도체 장비 투자 역대 최대 삼성전자 평택캠퍼스 전경 올해 전 세계 반도체 ",
            "url": "https://news.naver.com/main/read.naver?mode=LSD&mid=sec&sid1=101&oid=015&aid=0004652238",
            "name": "하이닉스",
            "types": "IDM",
            "like_cnt": 37,
            "recom_react_cnt": 1365,
            "com_cnt": 15,
            "summaries": "['12일 반도체 업계에 따르면 국제반도체장비재료협회 SEMI 는 최근 보고서를 통해 올해 전 세계 반도체 장비 투자액이 전년 대비 10 증가해 사상 최대 규모인 980억달러 약 116조6000억원 에 달할 것으로 추정했다.', '국제반도체장비재료협회 분석 올해 반도체 장비 투자 역대 최대 삼성전자 평택캠퍼스 전경 올해 전 세계 반도체 장비투자 규모가 역대 최대를 기록할 것이라는 전망이 나왔다.', '부문별로는 파운드리 반도체 위탁생산 분야에 대한 투자가 전년 대비 13 증가해 올해 전체 반도체 장비 투자의 46 를 차지할 것으로 예상했다.']",
            "hashtag": [
                {
                    "hash1": "#반도체"
                },
                {
                    "hash2": "#장비"
                },
                {
                    "hash3": "#투자"
                },
                {
                    "hash4": "#올해"
                }
            ]
        }
    ],
    "list2": [
        {
            "size": "10.0ex",
            "text": "생산"
        },
        {
            "size": "10.0ex",
            "text": "화재"
        },
        {
            "size": "9.05ex",
            "text": "규제"
        },
        {
            "size": "9.05ex",
            "text": "문제"
        },
        {
            "size": "8.27ex",
            "text": "식품"
        },
        {
            "size": "6.91ex",
            "text": "마켓"
        },
        {
            "size": "6.75ex",
            "text": "선물"
        },
        {
            "size": "6.75ex",
            "text": "세트"
        },
        {
            "size": "6.75ex",
            "text": "프리미엄"
        },
        {
            "size": "6.75ex",
            "text": "호텔"
        },
        {
            "size": "6.29ex",
            "text": "중국"
        }
    ],
    "list3": [
        {
            "url": "https://news.naver.com/main/read.naver?mode=LSD&mid=sec&sid1=101&oid=417&aid=0000774592",
            "title": "삼성전자, 시총 468조원 ‘부동의 1위’… 네이버 3위 등극",
            "recom_react_cnt": 13151
        },
        {
            "url": "https://news.naver.com/main/read.naver?mode=LSD&mid=sec&sid1=105&oid=030&aid=0002993219",
            "title": "델 테크놀로지스, 친환경 소재 접목 고성능 노트북·모니터 출시",
            "recom_react_cnt": 4874
        },
        {
            "url": "https://news.naver.com/main/read.naver?mode=LSD&mid=sec&sid1=105&oid=016&aid=0001936810",
            "title": "“이게 150만원 실화야?” 삼성 야심작, 아이폰보다 비싸다?",
            "recom_react_cnt": 2215
        },
        {
            "url": "https://news.naver.com/main/read.naver?mode=LSD&mid=sec&sid1=104&oid=277&aid=0005029524",
            "title": "블룸버그 \"中, 韓 바짝 추격\"…기술패권 고삐 죄는 中",
            "recom_react_cnt": 1935
        },
        {
            "url": "https://news.naver.com/main/read.naver?mode=LSD&mid=sec&sid1=101&oid=014&aid=0004771276",
            "title": "[김경민의 적시타]LCD값 대폭락…국내기업 사실상 사업 철수",
            "recom_react_cnt": 1856
        },
        {
            "url": "https://news.naver.com/main/read.naver?mode=LSD&mid=sec&sid1=101&oid=448&aid=0000348802",
            "title": "美 긴축 우려 완화에 코스피, 1.54% '반등'",
            "recom_react_cnt": 1582
        },
        {
            "url": "https://news.naver.com/main/read.naver?mode=LSD&mid=sec&sid1=101&oid=015&aid=0004651905",
            "title": "이재용도 찾아간 그곳…'60평 화재' 사고에 삼성 '초비상'",
            "recom_react_cnt": 1454
        },
        {
            "url": "https://news.naver.com/main/read.naver?mode=LSD&mid=sec&sid1=101&oid=015&aid=0004652238",
            "title": "삼성·하이닉스 '매출 신기록' 이유 있네…\"韓, 반도체장비 최대 투자국\"",
            "recom_react_cnt": 1365
        },
        {
            "url": "https://news.naver.com/main/read.naver?mode=LSD&mid=sec&sid1=100&oid=028&aid=0002575286",
            "title": "10대 그룹 CEO 만난 이재명 “불필요한 규제 과감하게 철폐”",
            "recom_react_cnt": 1340
        },
        {
            "url": "https://news.naver.com/main/read.naver?mode=LSD&mid=sec&sid1=105&oid=629&aid=0000126831",
            "title": "삼성전자, CJ제일제당과 손잡고 '비스포크 큐커' 대중화 나선다",
            "recom_react_cnt": 1247
        },
        {
            "url": "https://news.naver.com/main/read.naver?mode=LSD&mid=sec&sid1=101&oid=119&aid=0002566284",
            "title": "신라호텔, '프리미엄' 상품 강화한 설 선물세트 출시",
            "recom_react_cnt": 1065
        }
    ]
}